matrecord_suggestion/__init__.py
matrecord_suggestion/autocorrect book.txt
matrecord_suggestion/autocorrect.py
matrecord_suggestion-0.2.dist-info/LICENSE
matrecord_suggestion-0.2.dist-info/METADATA
matrecord_suggestion-0.2.dist-info/WHEEL
matrecord_suggestion-0.2.dist-info/top_level.txt
matrecord_suggestion-0.2.dist-info/RECORD
